<?xml version="1.0" encoding="UTF-8"?>
<core-beans>
	 <!-- 
	 <service url="http://172.16.3.24:1080/solr/">
	 <service url="http://10.0.0.161:5085/solr/">
	 -->
	 
	 <!-- <service url="http://solr.xiu.com:4746/solr/"> --> 
	 <!-- <service url="http://solr.xiu.com:3736/solr2/"> -->
	 <service url="http://solrxiu.xiu.com:47466/solr2/">
		<core name="xiu" class="com.xiu.search.core.solr.model.GoodsSolrModel" >
			<connectionTimeout>5000</connectionTimeout>
			<maxRetries>3</maxRetries>
			<maxTotalConnections>30</maxTotalConnections>
			<defaultMaxConnectionsPerHost>15</defaultMaxConnectionsPerHost>
		</core>
	</service>
	<!-- <service url="http://solrsku.xiu.com:3738/solr/"> -->
	<service url="http://solrsku.xiu.com:3739/solr/">
		<core name="sku" class="com.xiu.search.core.solr.model.XiuSKUIndexModel" >
			<connectionTimeout>5000</connectionTimeout>
			<maxRetries>3</maxRetries>
			<maxTotalConnections>30</maxTotalConnections>
			<defaultMaxConnectionsPerHost>15</defaultMaxConnectionsPerHost>
		</core>
	</service>
	<!-- <service url="http://solr.xiu.com:3738/solr/"> -->
	<service url="http://oclass.xiu.com:3738/solr/">
		<core name="suggest" class="com.xiu.search.core.solr.model.SuggestSolrModel" >
			<connectionTimeout>5000</connectionTimeout>
			<maxRetries>3</maxRetries>
			<maxTotalConnections>30</maxTotalConnections>
			<defaultMaxConnectionsPerHost>15</defaultMaxConnectionsPerHost>
		</core>
		<core name="oclass" class="com.xiu.search.core.solr.model.OclassSolrModel" >
			<connectionTimeout>5000</connectionTimeout>
			<maxRetries>3</maxRetries>
			<maxTotalConnections>30</maxTotalConnections>
			<defaultMaxConnectionsPerHost>15</defaultMaxConnectionsPerHost>
		</core>
		<core name="lexicon" class="com.xiu.solr.lexicon.client.model.LexiconBaseModel" >
			<connectionTimeout>5000</connectionTimeout>
			<maxRetries>3</maxRetries>
			<maxTotalConnections>30</maxTotalConnections>
			<defaultMaxConnectionsPerHost>15</defaultMaxConnectionsPerHost>
		</core>
	</service>
	<!-- 
	<service url="http://localhost/lexicon-web/">
		<core name="lexicon" class="com.xiu.solr.lexicon.client.model.LexiconBaseModel" >
			<connectionTimeout>5000</connectionTimeout>
			<maxRetries>3</maxRetries>
			<maxTotalConnections>30</maxTotalConnections>
			<defaultMaxConnectionsPerHost>15</defaultMaxConnectionsPerHost>
		</core>
	</service>
	 -->
</core-beans>